qsharp_widgets/__init__.py
qsharp_widgets/static/index.css
qsharp_widgets/static/index.js
qsharp_widgets-1.25.1.dist-info/METADATA
qsharp_widgets-1.25.1.dist-info/WHEEL
qsharp_widgets-1.25.1.dist-info/RECORD
