Metadata-Version: 2.4
Name: qsharp-widgets
Version: 1.25.1
Requires-Dist: anywidget>=0.9.21
Provides-Extra: dev
Requires-Dist: jupyterlab; extra == 'dev'
Requires-Dist: watchfiles; extra == 'dev'
